gptcmd/__init__.py
gptcmd/cli.py
gptcmd/config.py
gptcmd/config_sample.toml
gptcmd/macros.py
gptcmd/message.py
gptcmd/llm/__init__.py
gptcmd/llm/openai.py
gptcmd-2.3.3.dist-info/licenses/COPYING.txt
gptcmd-2.3.3.dist-info/METADATA
gptcmd-2.3.3.dist-info/WHEEL
gptcmd-2.3.3.dist-info/entry_points.txt
gptcmd-2.3.3.dist-info/top_level.txt
gptcmd-2.3.3.dist-info/RECORD
