Metadata-Version: 2.4
Name: gptcmd
Version: 2.3.3
Summary: Command line GPT conversation and experimentation environment
Author-email: Bill Dengler <codeofdusk@gmail.com>
License-Expression: MPL-2.0
Project-URL: Homepage, https://github.com/codeofdusk/gptcmd
Project-URL: Bug Tracker, https://github.com/codeofdusk/gptcmd/issues
Classifier: Programming Language :: Python :: 3
Classifier: Operating System :: OS Independent
Requires-Python: >=3.8.6
License-File: COPYING.txt
Requires-Dist: openai<3.0.0,>=1.54.0
Requires-Dist: tomli<2.0.0,>=1.1.0; python_version < "3.11"
Requires-Dist: backports.strenum<2.0.0,>=1.3.1; python_version < "3.11"
Requires-Dist: importlib_metadata>=3.6; python_version < "3.10"
Requires-Dist: packaging>=23.0
Dynamic: license-file
